kcai/__init__.py
kcai/__main__.py
kcai/_version_.py
kcai/dependancy.py
kcai-0.0.1.dist-info/METADATA
kcai-0.0.1.dist-info/WHEEL
kcai-0.0.1.dist-info/entry_points.txt
kcai-0.0.1.dist-info/top_level.txt
kcai-0.0.1.dist-info/RECORD
